odoo/addons/delivery_carrier_service_level/README.rst
odoo/addons/delivery_carrier_service_level/__init__.py
odoo/addons/delivery_carrier_service_level/__manifest__.py
odoo/addons/delivery_carrier_service_level/i18n/delivery_carrier_service_level.pot
odoo/addons/delivery_carrier_service_level/models/__init__.py
odoo/addons/delivery_carrier_service_level/models/carrier_service_level.py
odoo/addons/delivery_carrier_service_level/models/stock_picking.py
odoo/addons/delivery_carrier_service_level/readme/CONFIGURE.rst
odoo/addons/delivery_carrier_service_level/readme/CONTRIBUTORS.rst
odoo/addons/delivery_carrier_service_level/readme/DESCRIPTION.rst
odoo/addons/delivery_carrier_service_level/readme/USAGE.rst
odoo/addons/delivery_carrier_service_level/security/ir.model.access.csv
odoo/addons/delivery_carrier_service_level/static/description/icon.png
odoo/addons/delivery_carrier_service_level/static/description/index.html
odoo/addons/delivery_carrier_service_level/views/carrier_service_level.xml
odoo/addons/delivery_carrier_service_level/views/stock_picking.xml
odoo13_addon_delivery_carrier_service_level-13.0.1.0.2.dist-info/METADATA
odoo13_addon_delivery_carrier_service_level-13.0.1.0.2.dist-info/WHEEL
odoo13_addon_delivery_carrier_service_level-13.0.1.0.2.dist-info/top_level.txt
odoo13_addon_delivery_carrier_service_level-13.0.1.0.2.dist-info/RECORD
